eltiempoes/__init__.py
eltiempoes/constants.py
eltiempoes/main.py
eltiempoes/web_scraping.py
eltiempoes/utils/__init__.py
eltiempoes/utils/create_urls.py
python_eltiempoes-0.0.5.dist-info/LICENSE
python_eltiempoes-0.0.5.dist-info/METADATA
python_eltiempoes-0.0.5.dist-info/WHEEL
python_eltiempoes-0.0.5.dist-info/top_level.txt
python_eltiempoes-0.0.5.dist-info/RECORD
