Metadata-Version: 2.1
Name: python-eltiempoes
Version: 0.0.5
Author: Francisco Puig
Keywords: weather,elTiempo.es
Classifier: Programming Language :: Python :: 3.8
Classifier: Programming Language :: Python :: 3.9
Classifier: Programming Language :: Python :: 3.10
Classifier: License :: OSI Approved :: MIT License
Classifier: Operating System :: MacOS
Classifier: Operating System :: Microsoft
Classifier: Operating System :: POSIX :: Linux
Requires-Python: >=3.6
License-File: LICENSE
Requires-Dist: beautifulsoup4 (==4.11.1)
Requires-Dist: requests (==2.27.1)
Requires-Dist: Unidecode (==1.3.4)
